drf_custom_viewsets/__init__.py
drf_custom_viewsets/models.py
drf_custom_viewsets/viewsets.py
drf_custom_viewsets/static/css/drf_custom_viewsets.css
drf_custom_viewsets/static/js/drf_custom_viewsets.js
drf_custom_viewsets/templates/drf_custom_viewsets/base.html
rest_framework_custom_viewsets-0.0.3.dist-info/DESCRIPTION.rst
rest_framework_custom_viewsets-0.0.3.dist-info/METADATA
rest_framework_custom_viewsets-0.0.3.dist-info/RECORD
rest_framework_custom_viewsets-0.0.3.dist-info/WHEEL
rest_framework_custom_viewsets-0.0.3.dist-info/metadata.json
rest_framework_custom_viewsets-0.0.3.dist-info/top_level.txt
