Metadata-Version: 2.0
Name: rest-framework-custom-viewsets
Version: 0.0.3
Summary: Django ModelViewSet extended for per view base extensions like Serializer Classes etc.
Home-page: https://github.com/Darwesh27/rest_framework_custom_viewsets
Author: Malik Junaid
Author-email: malik.junaid27@gmail.com
License: BSD
Keywords: rest_framework_custom_viewsets
Platform: UNKNOWN
Classifier: Development Status :: 3 - Alpha
Classifier: Framework :: Django
Classifier: Framework :: Django :: 1.8
Classifier: Framework :: Django :: 1.9
Classifier: Intended Audience :: Developers
Classifier: License :: OSI Approved :: BSD License
Classifier: Natural Language :: English
Classifier: Programming Language :: Python :: 2
Classifier: Programming Language :: Python :: 2.7
Classifier: Programming Language :: Python :: 3
Classifier: Programming Language :: Python :: 3.3
Classifier: Programming Language :: Python :: 3.4
Classifier: Programming Language :: Python :: 3.5
